jaclang_streamlit/__init__.py
jaclang_streamlit/app_test.py
jaclang_streamlit/commands.py
jaclang_streamlit/dot_viewer.py
jaclang_streamlit-0.0.3.dist-info/METADATA
jaclang_streamlit-0.0.3.dist-info/WHEEL
jaclang_streamlit-0.0.3.dist-info/entry_points.txt
jaclang_streamlit-0.0.3.dist-info/RECORD
