Metadata-Version: 2.1
Name: jaclang-streamlit
Version: 0.0.3
Summary: This Jac plugin adds a streamlit command line option for conveniently running streamlit apps written in Jac.
Home-page: https://jaseci.org
License: MIT
Keywords: jac,jaclang,jaseci,streamlit,visualization,graph
Author: Jason Mars
Author-email: jason@jaseci.org
Requires-Python: >=3.12.0,<4.0.0
Classifier: License :: OSI Approved :: MIT License
Classifier: Programming Language :: Python :: 3
Classifier: Programming Language :: Python :: 3.12
Requires-Dist: pydot (>=3.0.1,<4.0.0)
Requires-Dist: streamlit (>=1.38.0,<2.0.0)
Requires-Dist: streamlit-agraph (>=0.0.45,<0.0.46)
Project-URL: Documentation, https://jac-lang.org
Project-URL: Repository, https://github.com/Jaseci-Labs/jaclang
